{"word": "abhorrent", "rank": "15642", "popularity": "1213.6", "extra": {}, "results": [{"info": {"word": "abhorrent", "type": "s", "order": "01", "extra": {}}, "synonym": ["abhorrent", "detestable", "obscene", "repugnant", "repulsive"], "antonyms": [], "definition": "offensive to the mind", "examples": ["an abhorrent deed", "the obscene massacre at Wounded Knee", "morally repugnant customs", "repulsive behavior", "the most repulsive character in recent novels"], "hyponyms": [], "hypernyms": [], "entailments": []}]}