{"word": "agues", "rank": "23732", "popularity": 222.308, "extra": {}, "results": [{"info": {"word": "ague", "type": "n", "order": "01", "extra": {}}, "synonym": ["ague"], "antonyms": [], "definition": "a fit of shivering or shaking", "examples": [], "hyponyms": [], "hypernyms": ["illness.n.01"], "entailments": []}, {"info": {"word": "ague", "type": "n", "order": "02", "extra": {}}, "synonym": ["ague", "chills_and_fever"], "antonyms": [], "definition": "successive stages of chills and fever that is a symptom of malaria", "examples": [], "hyponyms": ["quartan.n.01"], "hypernyms": ["symptom.n.01"], "entailments": []}, {"info": {"word": "acute_accent", "type": "n", "order": "01", "extra": {}}, "synonym": ["acute_accent", "acute", "ague"], "antonyms": [], "definition": "a mark (') placed above a vowel to indicate pronunciation", "examples": [], "hyponyms": [], "hypernyms": ["accent.n.05"], "entailments": []}]}