{"word": "beaten", "rank": "2899", "popularity": "26513.2", "extra": {}, "results": [{"info": {"word": "beat", "type": "v", "order": "01", "extra": {}}, "synonym": ["beat", "beat_out", "crush", "shell", "trounce", "vanquish"], "antonyms": [], "definition": "come out better in a competition, race, or conflict", "examples": ["Agassi beat Becker in the tennis championship", "We beat the competition", "Harvard defeated Yale in the last football game"], "hyponyms": ["cheat.v.02", "checkmate.v.01", "cream.v.02", "eliminate.v.06", "get_the_best.v.01", "get_the_jump.v.01", "immobilize.v.03", "outdo.v.02", "outfight.v.01", "outplay.v.01", "outpoint.v.02", "overcome.v.02", "overpower.v.01", "spread-eagle.v.05", "surpass.v.02", "walk_over.v.01", "whomp.v.02", "worst.v.01"], "hypernyms": ["get_the_better_of.v.01"], "entailments": ["win.v.01"]}, {"info": {"word": "beat", "type": "v", "order": "02", "extra": {}}, "synonym": ["beat", "beat_up", "work_over"], "antonyms": [], "definition": "give a beating to; subject to a beating, either as a punishment or as an act of aggression", "examples": ["Thugs beat him up when he walked down the street late at night", "The teacher used to beat the students"], "hyponyms": ["belabour.v.02", "cane.v.01", "clobber.v.01", "flog.v.01", "knock_cold.v.01", "pistol-whip.v.01", "rough_up.v.01", "soak.v.05", "spank.v.01", "strong-arm.v.03", "thrash.v.01"], "hypernyms": [], "entailments": ["hit.v.03"]}, {"info": {"word": "beat", "type": "v", "order": "03", "extra": {}}, "synonym": ["beat"], "antonyms": [], "definition": "hit repeatedly", "examples": ["beat on the door", "beat the table with his shoe"], "hyponyms": ["bastinado.v.01", "beat.v.20", "beetle.v.03", "deck.v.03", "full.v.01", "hammer.v.01", "paste.v.02", "thrash.v.06", "whang.v.01"], "hypernyms": ["strike.v.01"], "entailments": []}, {"info": {"word": "beat", "type": "v", "order": "04", "extra": {}}, "synonym": ["beat", "pound", "thump"], "antonyms": [], "definition": "move rhythmically", "examples": ["Her heart was beating fast"], "hyponyms": ["flap.v.02", "palpitate.v.03", "pulsate.v.01", "thrash.v.04"], "hypernyms": ["move.v.03"], "entailments": []}, {"info": {"word": "beat", "type": "v", "order": "05", "extra": {}}, "synonym": ["beat"], "antonyms": [], "definition": "shape by beating", "examples": ["beat swords into ploughshares"], "hyponyms": ["forge.v.01"], "hypernyms": ["shape.v.02"], "entailments": []}, {"info": {"word": "drum", "type": "v", "order": "01", "extra": {}}, "synonym": ["drum", "beat", "thrum"], "antonyms": [], "definition": "make a rhythmic sound", "examples": ["Rain drummed against the windshield", "The drums beat all night"], "hyponyms": [], "hypernyms": ["sound.v.02"], "entailments": []}, {"info": {"word": "beat", "type": "v", "order": "07", "extra": {}}, "synonym": ["beat"], "antonyms": [], "definition": "glare or strike with great intensity", "examples": ["The sun was beating down on us"], "hyponyms": [], "hypernyms": ["glare.v.03"], "entailments": []}, {"info": {"word": "beat", "type": "v", "order": "08", "extra": {}}, "synonym": ["beat", "flap"], "antonyms": [], "definition": "move with a thrashing motion", "examples": ["The bird flapped its wings", "The eagle beat its wings and soared high into the sky"], "hyponyms": ["bate.v.02", "clap.v.02", "flutter.v.03"], "hypernyms": ["move.v.02"], "entailments": []}, {"info": {"word": "beat", "type": "v", "order": "09", "extra": {}}, "synonym": ["beat"], "antonyms": [], "definition": "sail with much tacking or with difficulty", "examples": ["The boat beat in the strong wind"], "hyponyms": [], "hypernyms": ["sail.v.03"], "entailments": []}, {"info": {"word": "beat", "type": "v", "order": "10", "extra": {}}, "synonym": ["beat", "scramble"], "antonyms": [], "definition": "stir vigorously", "examples": ["beat the egg whites", "beat the cream"], "hyponyms": ["cream.v.01", "whisk.v.04"], "hypernyms": ["agitate.v.06"], "entailments": []}, {"info": {"word": "beat", "type": "v", "order": "11", "extra": {}}, "synonym": ["beat"], "antonyms": [], "definition": "strike (a part of one's own body) repeatedly, as in great emotion or in accompaniment to music", "examples": ["beat one's breast", "beat one's foot rhythmically"], "hyponyms": [], "hypernyms": ["strike.v.01"], "entailments": []}, {"info": {"word": "beat", "type": "v", "order": "12", "extra": {}}, "synonym": ["beat"], "antonyms": [], "definition": "be superior", "examples": ["Reading beats watching television", "This sure beats work!"], "hyponyms": [], "hypernyms": ["be.v.01"], "entailments": []}, {"info": {"word": "beat", "type": "v", "order": "13", "extra": {}}, "synonym": ["beat", "bunk"], "antonyms": [], "definition": "avoid paying", "examples": ["beat the subway fare"], "hyponyms": [], "hypernyms": ["cheat.v.01"], "entailments": []}, {"info": {"word": "tick", "type": "v", "order": "02", "extra": {}}, "synonym": ["tick", "ticktock", "ticktack", "beat"], "antonyms": [], "definition": "make a sound like a clock or a timer", "examples": ["the clocks were ticking", "the grandfather clock beat midnight"], "hyponyms": [], "hypernyms": ["sound.v.02"], "entailments": []}, {"info": {"word": "beat", "type": "v", "order": "15", "extra": {}}, "synonym": ["beat", "flap"], "antonyms": [], "definition": "move with a flapping motion", "examples": ["The bird's wings were flapping"], "hyponyms": ["clap.v.05", "flail.v.02"], "hypernyms": ["move.v.03"], "entailments": []}, {"info": {"word": "beat", "type": "v", "order": "16", "extra": {}}, "synonym": ["beat"], "antonyms": [], "definition": "indicate by beating, as with the fingers or drumsticks", "examples": ["Beat the rhythm"], "hyponyms": ["beat_out.v.02"], "hypernyms": [], "entailments": []}, {"info": {"word": "pulsate", "type": "v", "order": "02", "extra": {}}, "synonym": ["pulsate", "beat", "quiver"], "antonyms": [], "definition": "move with or as if with a regular alternating motion", "examples": ["the city pulsated with music and excitement"], "hyponyms": [], "hypernyms": ["move.v.03"], "entailments": []}, {"info": {"word": "beat", "type": "v", "order": "18", "extra": {}}, "synonym": ["beat"], "antonyms": [], "definition": "make by pounding or trampling", "examples": ["beat a path through the forest"], "hyponyms": [], "hypernyms": ["make.v.03"], "entailments": ["tread.v.02"]}, {"info": {"word": "beat", "type": "v", "order": "19", "extra": {}}, "synonym": ["beat"], "antonyms": [], "definition": "produce a rhythm by striking repeatedly", "examples": ["beat the drum"], "hyponyms": [], "hypernyms": ["play.v.07"], "entailments": []}, {"info": {"word": "beat", "type": "v", "order": "20", "extra": {}}, "synonym": ["beat"], "antonyms": [], "definition": "strike (water or bushes) repeatedly to rouse animals for hunting", "examples": [], "hyponyms": [], "hypernyms": ["beat.v.03"], "entailments": []}, {"info": {"word": "outwit", "type": "v", "order": "01", "extra": {}}, "synonym": ["outwit", "overreach", "outsmart", "outfox", "beat", "circumvent"], "antonyms": [], "definition": "beat through cleverness and wit", "examples": ["I beat the traffic", "She outfoxed her competitors"], "hyponyms": [], "hypernyms": ["surpass.v.02"], "entailments": []}, {"info": {"word": "perplex", "type": "v", "order": "01", "extra": {}}, "synonym": ["perplex", "vex", "stick", "get", "puzzle", "mystify", "baffle", "beat", "pose", "bewilder", "flummox", "stupefy", "nonplus", "gravel", "amaze", "dumbfound"], "antonyms": [], "definition": "be a mystery or bewildering to", "examples": ["This beats me!", "Got me--I don't know the answer!", "a vexing problem", "This question really stuck me"], "hyponyms": ["elude.v.02", "riddle.v.02", "stump.v.01"], "hypernyms": ["confuse.v.02"], "entailments": []}, {"info": {"word": "exhaust", "type": "v", "order": "01", "extra": {}}, "synonym": ["exhaust", "wash_up", "beat", "tucker", "tucker_out"], "antonyms": [], "definition": "wear out completely", "examples": ["This kind of work exhausts me", "I'm beat", "He was all washed up after the exam"], "hyponyms": ["frazzle.v.02", "kill.v.13", "play.v.35"], "hypernyms": ["tire.v.02"], "entailments": []}, {"info": {"word": "beaten", "type": "a", "order": "01", "extra": {}}, "synonym": ["beaten"], "antonyms": [], "definition": "formed or made thin by hammering", "examples": ["beaten gold"], "hyponyms": [], "hypernyms": [], "entailments": []}, {"info": {"word": "beaten", "type": "s", "order": "02", "extra": {}}, "synonym": ["beaten"], "antonyms": [], "definition": "much trodden and worn smooth or bare", "examples": ["did not stray from the beaten path"], "hyponyms": [], "hypernyms": [], "entailments": []}]}