{"word": "catastrophe", "rank": "6712", "popularity": "8570.36", "extra": {}, "results": [{"info": {"word": "calamity", "type": "n", "order": "01", "extra": {}}, "synonym": ["calamity", "catastrophe", "disaster", "tragedy", "cataclysm"], "antonyms": [], "definition": "an event resulting in great loss and misfortune", "examples": ["the whole city was affected by the irremediable calamity", "the earthquake was a disaster"], "hyponyms": ["act_of_god.n.01", "apocalypse.n.01", "famine.n.02", "kiss_of_death.n.01", "meltdown.n.02", "plague.n.04", "tidal_wave.n.02", "tsunami.n.01", "visitation.n.02"], "hypernyms": ["misfortune.n.01"], "entailments": []}, {"info": {"word": "catastrophe", "type": "n", "order": "02", "extra": {}}, "synonym": ["catastrophe", "disaster"], "antonyms": [], "definition": "a state of extreme (usually irremediable) ruin and misfortune", "examples": ["lack of funds has resulted in a catastrophe for our school system", "his policies were a disaster"], "hyponyms": [], "hypernyms": ["adversity.n.01"], "entailments": []}, {"info": {"word": "catastrophe", "type": "n", "order": "03", "extra": {}}, "synonym": ["catastrophe", "cataclysm"], "antonyms": [], "definition": "a sudden violent change in the earth's surface", "examples": [], "hyponyms": ["nuclear_winter.n.01"], "hypernyms": ["geological_phenomenon.n.01"], "entailments": []}]}