{"word": "cockroach", "rank": "24343", "popularity": 194.61900000000003, "extra": {}, "results": [{"info": {"word": "cockroach", "type": "n", "order": "01", "extra": {}}, "synonym": ["cockroach", "roach"], "antonyms": [], "definition": "any of numerous chiefly nocturnal insects; some are domestic pests", "examples": [], "hyponyms": ["american_cockroach.n.01", "australian_cockroach.n.01", "german_cockroach.n.01", "giant_cockroach.n.01", "oriental_cockroach.n.01"], "hypernyms": ["dictyopterous_insect.n.01"], "entailments": []}]}