{"word": "condescend", "rank": "11185", "popularity": "2984.95", "extra": {}, "results": [{"info": {"word": "condescend", "type": "v", "order": "01", "extra": {}}, "synonym": ["condescend"], "antonyms": [], "definition": "behave in a patronizing and condescending manner", "examples": [], "hyponyms": [], "hypernyms": ["act.v.01"], "entailments": []}, {"info": {"word": "condescend", "type": "v", "order": "02", "extra": {}}, "synonym": ["condescend", "deign", "descend"], "antonyms": [], "definition": "do something that one considers to be below one's dignity", "examples": [], "hyponyms": [], "hypernyms": ["act.v.01"], "entailments": []}, {"info": {"word": "condescend", "type": "v", "order": "03", "extra": {}}, "synonym": ["condescend", "stoop", "lower_oneself"], "antonyms": [], "definition": "debase oneself morally, act in an undignified, unworthy, or dishonorable way", "examples": ["I won't stoop to reading other people's mail"], "hyponyms": [], "hypernyms": ["act.v.01"], "entailments": []}, {"info": {"word": "patronize", "type": "v", "order": "03", "extra": {}}, "synonym": ["patronize", "patronise", "condescend"], "antonyms": [], "definition": "treat condescendingly", "examples": [], "hyponyms": ["stoop_to.v.01"], "hypernyms": ["interact.v.01"], "entailments": []}]}