{"word": "creative", "rank": "7729", "popularity": "6755.49", "extra": {}, "results": [{"info": {"word": "creative", "type": "a", "order": "01", "extra": {}}, "synonym": ["creative", "originative"], "antonyms": [], "definition": "having the ability or power to create", "examples": ["a creative imagination"], "hyponyms": [], "hypernyms": [], "entailments": []}, {"info": {"word": "creative", "type": "s", "order": "02", "extra": {}}, "synonym": ["creative"], "antonyms": [], "definition": "promoting construction or creation", "examples": ["creative work"], "hyponyms": [], "hypernyms": [], "entailments": []}]}