{"word": "credence", "rank": "13855", "popularity": "1710.43", "extra": {}, "results": [{"info": {"word": "credence", "type": "n", "order": "01", "extra": {}}, "synonym": ["credence", "acceptance"], "antonyms": [], "definition": "the mental attitude that something is believable and should be accepted as true", "examples": ["he gave credence to the gossip", "acceptance of Newtonian mechanics was unquestioned for 200 years"], "hyponyms": ["fatalism.n.01", "recognition.n.07"], "hypernyms": ["attitude.n.01"], "entailments": []}, {"info": {"word": "credenza", "type": "n", "order": "01", "extra": {}}, "synonym": ["credenza", "credence"], "antonyms": [], "definition": "a kind of sideboard or buffet", "examples": [], "hyponyms": [], "hypernyms": ["buffet.n.01"], "entailments": []}]}