{"word": "crowns", "rank": "6040", "popularity": "10158.9", "extra": {}, "results": [{"info": {"word": "crown", "type": "n", "order": "01", "extra": {}}, "synonym": ["Crown"], "antonyms": [], "definition": "the Crown (or the reigning monarch) as the symbol of the power and authority of a monarchy", "examples": ["the colonies revolted against the Crown"], "hyponyms": [], "hypernyms": ["symbol.n.01"], "entailments": []}, {"info": {"word": "crown", "type": "n", "order": "02", "extra": {}}, "synonym": ["crown"], "antonyms": [], "definition": "the part of a tooth above the gum that is covered with enamel", "examples": [], "hyponyms": [], "hypernyms": ["top.n.01"], "entailments": []}, {"info": {"word": "crown", "type": "n", "order": "03", "extra": {}}, "synonym": ["crown"], "antonyms": [], "definition": "a wreath or garland worn on the head to signify victory", "examples": [], "hyponyms": ["crown_of_thorns.n.03"], "hypernyms": ["wreath.n.01"], "entailments": []}, {"info": {"word": "crown", "type": "n", "order": "04", "extra": {}}, "synonym": ["crown", "diadem"], "antonyms": [], "definition": "an ornamental jeweled headdress signifying sovereignty", "examples": [], "hyponyms": ["coronet.n.01"], "hypernyms": ["crown_jewels.n.01", "jewelled_headdress.n.01"], "entailments": []}, {"info": {"word": "crown", "type": "n", "order": "05", "extra": {}}, "synonym": ["crown"], "antonyms": [], "definition": "the part of a hat (the vertex) that covers the crown of the head", "examples": [], "hyponyms": [], "hypernyms": ["vertex.n.02"], "entailments": []}, {"info": {"word": "crown", "type": "n", "order": "06", "extra": {}}, "synonym": ["crown"], "antonyms": [], "definition": "an English coin worth 5 shillings", "examples": [], "hyponyms": [], "hypernyms": ["coin.n.01"], "entailments": []}, {"info": {"word": "crown", "type": "n", "order": "07", "extra": {}}, "synonym": ["crown", "treetop"], "antonyms": [], "definition": "the upper branches and leaves of a tree or other plant", "examples": [], "hyponyms": ["capitulum.n.03"], "hypernyms": ["top.n.01"], "entailments": []}, {"info": {"word": "peak", "type": "n", "order": "04", "extra": {}}, "synonym": ["peak", "crown", "crest", "top", "tip", "summit"], "antonyms": [], "definition": "the top or extreme point of something (usually a mountain or hill)", "examples": ["the view from the peak was magnificent", "they clambered to the tip of Monadnock", "the region is a few molecules wide at the summit"], "hyponyms": ["hilltop.n.01", "mountain_peak.n.01", "pinnacle.n.03"], "hypernyms": ["topographic_point.n.01"], "entailments": []}, {"info": {"word": "pennant", "type": "n", "order": "01", "extra": {}}, "synonym": ["pennant", "crown"], "antonyms": [], "definition": "the award given to the champion", "examples": [], "hyponyms": [], "hypernyms": ["award.n.02"], "entailments": []}, {"info": {"word": "pate", "type": "n", "order": "02", "extra": {}}, "synonym": ["pate", "poll", "crown"], "antonyms": [], "definition": "the top of the head", "examples": [], "hyponyms": ["tonsure.n.01"], "hypernyms": ["top.n.02"], "entailments": []}, {"info": {"word": "crown", "type": "n", "order": "11", "extra": {}}, "synonym": ["crown", "crownwork", "jacket", "jacket_crown", "cap"], "antonyms": [], "definition": "(dentistry) dental appliance consisting of an artificial crown for a broken or decayed tooth", "examples": ["tomorrow my dentist will fit me for a crown"], "hyponyms": [], "hypernyms": ["dental_appliance.n.01"], "entailments": []}, {"info": {"word": "crown", "type": "n", "order": "12", "extra": {}}, "synonym": ["crown", "crest"], "antonyms": [], "definition": "the center of a cambered road", "examples": [], "hyponyms": [], "hypernyms": ["top.n.02"], "entailments": []}, {"info": {"word": "crown", "type": "v", "order": "01", "extra": {}}, "synonym": ["crown", "coronate"], "antonyms": [], "definition": "invest with regal power; enthrone", "examples": ["The prince was crowned in Westminster Abbey"], "hyponyms": [], "hypernyms": ["invest.v.04"], "entailments": []}, {"info": {"word": "crown", "type": "v", "order": "02", "extra": {}}, "synonym": ["crown", "top"], "antonyms": [], "definition": "be the culminating event", "examples": ["The speech crowned the meeting"], "hyponyms": [], "hypernyms": ["culminate.v.01"], "entailments": []}, {"info": {"word": "crown", "type": "v", "order": "03", "extra": {}}, "synonym": ["crown"], "antonyms": [], "definition": "form the topmost part of", "examples": ["A weather vane crowns the building"], "hyponyms": [], "hypernyms": ["head.v.07"], "entailments": []}, {"info": {"word": "crown", "type": "v", "order": "04", "extra": {}}, "synonym": ["crown"], "antonyms": [], "definition": "put an enamel cover on", "examples": ["crown my teeth"], "hyponyms": [], "hypernyms": ["cover.v.01"], "entailments": []}]}