{"word": "eightieth", "rank": "21877", "popularity": 333.06699999999995, "extra": {}, "results": [{"info": {"word": "eightieth", "type": "n", "order": "01", "extra": {}}, "synonym": ["eightieth"], "antonyms": [], "definition": "position 80 in a countable series of things", "examples": [], "hyponyms": [], "hypernyms": ["rank.n.02"], "entailments": []}, {"info": {"word": "eightieth", "type": "s", "order": "01", "extra": {}}, "synonym": ["eightieth", "80th"], "antonyms": [], "definition": "the ordinal number of eighty in counting order", "examples": [], "hyponyms": [], "hypernyms": [], "entailments": []}]}