{"word": "formation", "rank": "4084", "popularity": "17240.4", "extra": {}, "results": [{"info": {"word": "formation", "type": "n", "order": "01", "extra": {}}, "synonym": ["formation"], "antonyms": [], "definition": "an arrangement of people or things acting as a unit", "examples": ["a defensive formation", "a formation of planes"], "hyponyms": ["backfield.n.01", "center.n.08", "flank.n.01", "flight.n.01", "head.n.05", "line.n.01", "line.n.03", "military_formation.n.01", "rear.n.01", "secondary.n.01"], "hypernyms": ["arrangement.n.02"], "entailments": []}, {"info": {"word": "formation", "type": "n", "order": "02", "extra": {}}, "synonym": ["formation", "shaping"], "antonyms": [], "definition": "the act of fabricating something in a particular shape", "examples": [], "hyponyms": ["filing.n.03", "forging.n.01", "granulation.n.02", "grooving.n.01", "metalworking.n.01", "turning.n.06"], "hypernyms": ["fabrication.n.03"], "entailments": []}, {"info": {"word": "constitution", "type": "n", "order": "02", "extra": {}}, "synonym": ["constitution", "establishment", "formation", "organization", "organisation"], "antonyms": [], "definition": "the act of forming or establishing something", "examples": ["the constitution of a PTA group last year", "it was the establishment of his reputation", "he still remembers the organization of the club"], "hyponyms": ["collectivization.n.01", "colonization.n.01", "communization.n.02", "federation.n.03", "unionization.n.01"], "hypernyms": ["beginning.n.05"], "entailments": []}, {"info": {"word": "geological_formation", "type": "n", "order": "01", "extra": {}}, "synonym": ["geological_formation", "formation"], "antonyms": [], "definition": "(geology) the geological features of the earth", "examples": [], "hyponyms": ["aquifer.n.01", "beach.n.01", "cave.n.01", "cliff.n.01", "delta.n.01", "diapir.n.01", "folium.n.01", "foreshore.n.01", "ice_mass.n.01", "lakefront.n.01", "massif.n.01", "monocline.n.01", "mouth.n.04", "natural_depression.n.01", "natural_elevation.n.01", "oceanfront.n.01", "range.n.04", "relict.n.02", "ridge.n.03", "ridge.n.04", "shore.n.01", "slope.n.01", "spring.n.03", "talus.n.01", "vein.n.04", "volcanic_crater.n.01", "wall.n.05", "water_table.n.01"], "hypernyms": ["object.n.01"], "entailments": []}, {"info": {"word": "formation", "type": "n", "order": "05", "extra": {}}, "synonym": ["formation"], "antonyms": [], "definition": "a particular spatial arrangement", "examples": [], "hyponyms": ["raster.n.01", "rig.n.03", "split.n.08"], "hypernyms": ["placement.n.01"], "entailments": []}, {"info": {"word": "formation", "type": "n", "order": "06", "extra": {}}, "synonym": ["formation"], "antonyms": [], "definition": "natural process that causes something to form", "examples": ["the formation of gas in the intestine", "the formation of crystals", "the formation of pseudopods"], "hyponyms": ["incrustation.n.01", "reticulation.n.01"], "hypernyms": ["natural_process.n.01"], "entailments": []}, {"info": {"word": "formation", "type": "n", "order": "07", "extra": {}}, "synonym": ["formation"], "antonyms": [], "definition": "creation by mental activity", "examples": ["the formation of sentences", "the formation of memories"], "hyponyms": ["affixation.n.02"], "hypernyms": ["creating_by_mental_acts.n.01"], "entailments": []}]}