{"word": "freshness", "rank": "7054", "popularity": "7908.18", "extra": {}, "results": [{"info": {"word": "freshness", "type": "n", "order": "01", "extra": {}}, "synonym": ["freshness"], "antonyms": ["staleness"], "definition": "the property of being pure and fresh (as if newly made); not stale or deteriorated", "examples": ["she loved the freshness of newly baked bread", "the freshness of the air revived him"], "hyponyms": ["crispness.n.01"], "hypernyms": ["newness.n.01"], "entailments": []}, {"info": {"word": "freshness", "type": "n", "order": "02", "extra": {}}, "synonym": ["freshness", "novelty"], "antonyms": [], "definition": "originality by virtue of being refreshingly novel", "examples": [], "hyponyms": [], "hypernyms": ["originality.n.02"], "entailments": []}, {"info": {"word": "freshness", "type": "n", "order": "03", "extra": {}}, "synonym": ["freshness", "glow"], "antonyms": [], "definition": "an alert and refreshed state", "examples": [], "hyponyms": [], "hypernyms": ["good_health.n.01"], "entailments": []}, {"info": {"word": "novelty", "type": "n", "order": "02", "extra": {}}, "synonym": ["novelty", "freshness"], "antonyms": [], "definition": "originality by virtue of being new and surprising", "examples": [], "hyponyms": [], "hypernyms": ["originality.n.01"], "entailments": []}, {"info": {"word": "crust", "type": "n", "order": "03", "extra": {}}, "synonym": ["crust", "gall", "impertinence", "impudence", "insolence", "cheekiness", "freshness"], "antonyms": [], "definition": "the trait of being rude and impertinent; inclined to take liberties", "examples": [], "hyponyms": ["chutzpa.n.01"], "hypernyms": ["discourtesy.n.02"], "entailments": []}]}