{"word": "helix", "rank": "21692", "popularity": 345.725, "extra": {}, "results": [{"info": {"word": "helix", "type": "n", "order": "01", "extra": {}}, "synonym": ["helix", "spiral"], "antonyms": [], "definition": "a curve that lies on the surface of a cylinder or cone and cuts the element at a constant angle", "examples": [], "hyponyms": ["double_helix.n.01"], "hypernyms": ["curve.n.01"], "entailments": []}, {"info": {"word": "coil", "type": "n", "order": "01", "extra": {}}, "synonym": ["coil", "spiral", "volute", "whorl", "helix"], "antonyms": [], "definition": "a structure consisting of something wound in a continuous series of loops", "examples": ["a coil of rope"], "hyponyms": ["hank.n.01"], "hypernyms": ["structure.n.01"], "entailments": []}, {"info": {"word": "helix", "type": "n", "order": "03", "extra": {}}, "synonym": ["Helix", "genus_Helix"], "antonyms": [], "definition": "type genus of the family Helicidae", "examples": [], "hyponyms": [], "hypernyms": ["mollusk_genus.n.01"], "entailments": []}]}