{"word": "insoluble", "rank": "13844", "popularity": "1715.17", "extra": {}, "results": [{"info": {"word": "insoluble", "type": "a", "order": "01", "extra": {}}, "synonym": ["insoluble", "indissoluble"], "antonyms": [], "definition": "(of a substance) incapable of being dissolved", "examples": [], "hyponyms": [], "hypernyms": [], "entailments": []}, {"info": {"word": "insoluble", "type": "a", "order": "02", "extra": {}}, "synonym": ["insoluble"], "antonyms": ["soluble"], "definition": "admitting of no solution or explanation", "examples": ["an insoluble doubt"], "hyponyms": [], "hypernyms": [], "entailments": []}, {"info": {"word": "insoluble", "type": "s", "order": "03", "extra": {}}, "synonym": ["insoluble"], "antonyms": [], "definition": "without hope of solution", "examples": ["an insoluble problem"], "hyponyms": [], "hypernyms": [], "entailments": []}]}