{"word": "licit", "rank": "28271", "popularity": 72.7843, "extra": {}, "results": [{"info": {"word": "licit", "type": "a", "order": "01", "extra": {}}, "synonym": ["licit"], "antonyms": ["illicit"], "definition": "sanctioned by custom or morality especially sexual morality", "examples": ["a wife's licit love"], "hyponyms": [], "hypernyms": [], "entailments": []}, {"info": {"word": "lawful", "type": "s", "order": "04", "extra": {}}, "synonym": ["lawful", "legitimate", "licit"], "antonyms": [], "definition": "authorized, sanctioned by, or in accordance with law", "examples": ["a legitimate government"], "hyponyms": [], "hypernyms": [], "entailments": []}]}