{"word": "malayan", "rank": "19790", "popularity": "526.895", "extra": {}, "results": [{"info": {"word": "malay", "type": "n", "order": "01", "extra": {}}, "synonym": ["Malay", "Malayan"], "antonyms": [], "definition": "a member of a people inhabiting the northern Malay Peninsula and Malaysia and parts of the western Malay Archipelago", "examples": [], "hyponyms": [], "hypernyms": ["asian.n.01"], "entailments": []}, {"info": {"word": "malaysian", "type": "a", "order": "01", "extra": {}}, "synonym": ["Malaysian", "Malayan"], "antonyms": [], "definition": "of or relating to or characteristic of Malaysia", "examples": ["Malaysian police crack down hard on drug smugglers", "Malayan crocodiles"], "hyponyms": [], "hypernyms": [], "entailments": []}, {"info": {"word": "malay", "type": "a", "order": "01", "extra": {}}, "synonym": ["Malay", "Malayan"], "antonyms": [], "definition": "of or relating to or characteristic of the people or language of Malaysia and the northern Malay Peninsula and parts of the western Malay Archipelago", "examples": ["Malay peoples", "Malayan syllable structure"], "hyponyms": [], "hypernyms": [], "entailments": []}]}