{"word": "mooning", "rank": "22251", "popularity": 306.96, "extra": {}, "results": [{"info": {"word": "daydream", "type": "v", "order": "02", "extra": {}}, "synonym": ["daydream", "moon"], "antonyms": [], "definition": "have dreamlike musings or fantasies while awake", "examples": ["She looked out the window, daydreaming"], "hyponyms": [], "hypernyms": ["idle.v.02"], "entailments": []}, {"info": {"word": "moon", "type": "v", "order": "02", "extra": {}}, "synonym": ["moon", "moon_around", "moon_on"], "antonyms": [], "definition": "be idle in a listless or dreamy way", "examples": [], "hyponyms": [], "hypernyms": ["idle.v.02"], "entailments": []}, {"info": {"word": "moon", "type": "v", "order": "03", "extra": {}}, "synonym": ["moon"], "antonyms": [], "definition": "expose one's buttocks to", "examples": ["moon the audience"], "hyponyms": [], "hypernyms": ["expose.v.03"], "entailments": []}]}