{"word": "panache", "rank": "29655", "popularity": 50.6326, "extra": {}, "results": [{"info": {"word": "dash", "type": "n", "order": "01", "extra": {}}, "synonym": ["dash", "elan", "flair", "panache", "style"], "antonyms": [], "definition": "distinctive and stylish elegance", "examples": ["he wooed her with the confident dash of a cavalry officer"], "hyponyms": [], "hypernyms": ["elegance.n.01"], "entailments": []}, {"info": {"word": "panache", "type": "n", "order": "02", "extra": {}}, "synonym": ["panache"], "antonyms": [], "definition": "a feathered plume on a helmet", "examples": [], "hyponyms": [], "hypernyms": ["plume.n.02"], "entailments": []}]}