{"word": "partaken", "rank": "15591", "popularity": "1227.84", "extra": {}, "results": [{"info": {"word": "partake", "type": "v", "order": "01", "extra": {}}, "synonym": ["partake"], "antonyms": [], "definition": "have some of the qualities or attributes of something", "examples": [], "hyponyms": [], "hypernyms": ["share.v.01"], "entailments": []}, {"info": {"word": "partake", "type": "v", "order": "02", "extra": {}}, "synonym": ["partake", "share", "partake_in"], "antonyms": [], "definition": "have, give, or receive a share of", "examples": ["We shared the cake"], "hyponyms": ["cut_in.v.01"], "hypernyms": ["get.v.01"], "entailments": []}, {"info": {"word": "partake", "type": "v", "order": "03", "extra": {}}, "synonym": ["partake", "touch"], "antonyms": [], "definition": "consume", "examples": ["She didn't touch her food all night"], "hyponyms": ["receive.v.12"], "hypernyms": ["consume.v.02"], "entailments": []}]}