{"word": "pears", "rank": "12394", "popularity": "2307.73", "extra": {}, "results": [{"info": {"word": "pear", "type": "n", "order": "01", "extra": {}}, "synonym": ["pear"], "antonyms": [], "definition": "sweet juicy gritty-textured fruit available in many varieties", "examples": [], "hyponyms": ["anjou.n.02", "bartlett.n.03", "bosc.n.01", "seckel.n.01"], "hypernyms": ["edible_fruit.n.01", "pome.n.01"], "entailments": []}, {"info": {"word": "pear", "type": "n", "order": "02", "extra": {}}, "synonym": ["pear", "pear_tree", "Pyrus_communis"], "antonyms": [], "definition": "Old World tree having sweet gritty-textured juicy fruit; widely cultivated in many varieties", "examples": [], "hyponyms": [], "hypernyms": ["fruit_tree.n.01"], "entailments": []}]}