{"word": "prostitute", "rank": "14284", "popularity": "1574.35", "extra": {}, "results": [{"info": {"word": "prostitute", "type": "n", "order": "01", "extra": {}}, "synonym": ["prostitute", "cocotte", "whore", "harlot", "bawd", "tart", "cyprian", "fancy_woman", "working_girl", "sporting_lady", "lady_of_pleasure", "woman_of_the_street"], "antonyms": [], "definition": "a woman who engages in sexual intercourse for money", "examples": [], "hyponyms": ["call_girl.n.01", "camp_follower.n.01", "comfort_woman.n.01", "demimondaine.n.01", "streetwalker.n.01", "white_slave.n.01"], "hypernyms": ["woman.n.01"], "entailments": []}, {"info": {"word": "prostitute", "type": "v", "order": "01", "extra": {}}, "synonym": ["prostitute"], "antonyms": [], "definition": "sell one's body; exchange sex for money", "examples": [], "hyponyms": ["street-walk.v.01"], "hypernyms": ["sell.v.01"], "entailments": []}]}