{"word": "rarefy", "rank": "30148", "popularity": 44.3035, "extra": {}, "results": [{"info": {"word": "rarefy", "type": "v", "order": "01", "extra": {}}, "synonym": ["rarefy"], "antonyms": [], "definition": "lessen the density or solidity of", "examples": ["The bones are rarefied"], "hyponyms": [], "hypernyms": ["change.v.01"], "entailments": []}, {"info": {"word": "rarefy", "type": "v", "order": "02", "extra": {}}, "synonym": ["rarefy", "sublimate", "subtilize"], "antonyms": [], "definition": "make more subtle or refined", "examples": [], "hyponyms": [], "hypernyms": ["change.v.01"], "entailments": []}, {"info": {"word": "rarefy", "type": "v", "order": "03", "extra": {}}, "synonym": ["rarefy", "attenuate"], "antonyms": [], "definition": "weaken the consistency of (a chemical substance)", "examples": [], "hyponyms": [], "hypernyms": ["weaken.v.01"], "entailments": []}]}