{"word": "suppurate", "rank": "27976", "popularity": 79.1134, "extra": {}, "results": [{"info": {"word": "suppurate", "type": "v", "order": "01", "extra": {}}, "synonym": ["suppurate", "mature"], "antonyms": [], "definition": "cause to ripen and discharge pus", "examples": ["The oil suppurates the pustules"], "hyponyms": [], "hypernyms": ["draw.v.36"], "entailments": []}, {"info": {"word": "fester", "type": "v", "order": "01", "extra": {}}, "synonym": ["fester", "maturate", "suppurate"], "antonyms": [], "definition": "ripen and generate pus", "examples": ["her wounds are festering"], "hyponyms": [], "hypernyms": ["exhaust.v.05"], "entailments": []}]}