{"word": "totalitarian", "rank": "30100", "popularity": 45.0946, "extra": {}, "results": [{"info": {"word": "totalitarian", "type": "n", "order": "01", "extra": {}}, "synonym": ["totalitarian"], "antonyms": [], "definition": "an adherent of totalitarian principles or totalitarian government", "examples": [], "hyponyms": [], "hypernyms": ["disciple.n.01"], "entailments": []}, {"info": {"word": "totalitarian", "type": "s", "order": "01", "extra": {}}, "synonym": ["totalitarian"], "antonyms": [], "definition": "characterized by a government in which the political authority exercises absolute and centralized control", "examples": ["a totalitarian regime crushes all autonomous institutions in its drive to seize the human soul\"- Arthur M.Schlesinger, Jr."], "hyponyms": [], "hypernyms": [], "entailments": []}, {"info": {"word": "totalitarian", "type": "a", "order": "02", "extra": {}}, "synonym": ["totalitarian", "totalistic"], "antonyms": [], "definition": "of or relating to the principles of totalitarianism according to which the state regulates every realm of life", "examples": ["totalitarian theory and practice", "operating in a totalistic fashion"], "hyponyms": [], "hypernyms": [], "entailments": []}]}