{"word": "whish", "rank": "29977", "popularity": 46.6769, "extra": {}, "results": [{"info": {"word": "whish", "type": "v", "order": "01", "extra": {}}, "synonym": ["whish"], "antonyms": [], "definition": "make a sibilant sound", "examples": [], "hyponyms": [], "hypernyms": ["sound.v.02"], "entailments": []}, {"info": {"word": "whish", "type": "v", "order": "02", "extra": {}}, "synonym": ["whish"], "antonyms": [], "definition": "move with a whishing sound", "examples": ["The car whished past her"], "hyponyms": [], "hypernyms": ["travel.v.01"], "entailments": []}]}