{"title": "A life lesson from a volunteer firefighter", "talk_url": "mark_bezos_a_life_lesson_from_a_volunteer_firefighter", "release_date": "1300286460", "duration": "247.0", "image_url": "f4fe699b25bc6c68c8590abedba172cfc4c2b9aa_800x600.jpg", "tag": ["community", "compassion", "culture"], "description": "Volunteer firefighter Mark Bezos tells a story of an act of heroism that didn't go quite as expected -- but that taught him a big lesson: Don't wait to be a hero.", "author": "Mark Bezos", "keywords": "TED, talks, community, compassion, culture", "talk_id": "1096", "lang": ["el", "en", "vi", "ca", "it", "bg", "pt-BR", "cs", "et", "id", "es", "ru", "nl", "pt", "zh-Hans", "zh-Hant", "nb", "tr", "lv", "hr", "lt", "th", "tg", "ro", "pl", "fr", "hy", "sl", "fr-CA", "da", "fa", "hi", "fi", "hu", "ja", "he", "ka", "sr", "sq", "ko", "sv", "sk", "de", "ar", "uk", "mr", "my", "kk"], "download_link": "https://download.ted.com/talks/MarkBezos_2011U", "views": "3,124,367"}