{"title": "The 4 commandments of cities", "talk_url": "eduardo_paes_the_4_commandments_of_cities", "release_date": "1335453094", "duration": "741.0", "image_url": "f45ba92c04bdaedad7cf56e5182efb7953516601_800x600.jpg", "tag": ["Brazil", "TED Prize", "cities", "technology", "urban planning", "infrastructure", "South America"], "description": "Eduardo Paes is the mayor of Rio de Janeiro, a sprawling, complicated, beautiful city of 6.5 million. He shares four big ideas about leading Rio -- and all cities -- into the future, including bold (and do-able) infrastructure upgrades and how to make a city \"smarter.\"", "author": "Eduardo Paes", "keywords": "TED, talks, Brazil, TED Prize, cities, technology, urban planning, infrastructure, South America", "talk_id": "1429", "lang": ["el", "vi", "it", "ar", "pt-BR", "cs", "et", "id", "es", "ru", "pt", "nl", "zh-Hant", "tr", "zh-Hans", "en", "th", "ro", "pl", "fr", "bg", "fr-CA", "de", "fa", "ja", "he", "mg", "sr", "ko", "uk"], "download_link": "https://download.ted.com/talks/EduardoPaes_2012", "views": "895,373"}