{"title": "Behind the Great Firewall of China", "talk_url": "michael_anti_behind_the_great_firewall_of_china", "release_date": "1343660633", "duration": "1131.0", "image_url": "21cfdf7c11fdeaa2a4cfbffd24997ba2aa6f0830_1600x1200.jpg", "tag": ["Asia", "china", "global issues", "journalism", "social media", "technology"], "description": "Michael Anti (aka Jing Zhao) has been blogging from China for 12 years. Despite the control the central government has over the Internet -- \"All the servers are in Beijing\" -- he says that hundreds of millions of microbloggers are in fact creating the first national public sphere in the country's history, and shifting the balance of power in unexpected ways.", "author": "Michael Anti", "keywords": "TED, talks, Asia, china, global issues, journalism, social media, technology", "talk_id": "1523", "lang": ["en", "zh", "vi", "it", "ar", "pt-BR", "bg", "id", "es", "ru", "nl", "zh-Hant", "zh-Hans", "ro", "pl", "fr", "de", "fr-CA", "bo", "da", "ja", "he", "sr", "sq", "ko", "sl", "cs", "el", "fa", "hu", "pt"], "download_link": "https://download.ted.com/talks/MichaelAnti_2012G", "views": "1,649,571"}