{"title": "My days as a young rebel", "talk_url": "frank_gehry_my_days_as_a_young_rebel", "release_date": "1205372280", "duration": "2678.0", "image_url": "33968_480x360.jpg", "tag": ["architecture", "collaboration", "design", "global issues", "technology"], "description": "Before he was a legend, architect Frank Gehry takes a whistlestop tour of his early work, from his house in Venice Beach to the American Center in Paris, which was under construction (and much on his mind) when he gave this talk.", "author": "Frank Gehry", "keywords": "TED, talks, architecture, collaboration, design, global issues, technology", "talk_id": "231", "lang": ["en", "vi", "it", "ar", "pt-BR", "es", "ru", "pt", "zh-Hant", "lv", "zh-Hans", "ro", "pl", "fr", "bg", "de", "he", "ko", "ja"], "download_link": "https://download.ted.com/talks/FrankGehry_1990", "views": "699,739"}