{"title": "Architecture that repairs itself?", "talk_url": "rachel_armstrong_architecture_that_repairs_itself", "release_date": "1256634180", "duration": "452.0", "image_url": "126194_800x600.jpg", "tag": ["architecture", "art", "biology", "design", "life", "science", "sustainability", "technology", "global development", "industrial design"], "description": "Venice is sinking. To save it, Rachel Armstrong says we need to outgrow architecture made of inert materials and, well, make architecture that grows itself. She proposes a not-quite-alive material that does its own repairs and sequesters carbon, too.", "author": "Rachel Armstrong", "keywords": "TED, talks, architecture, art, biology, design, life, science, sustainability, technology, global development, industrial design", "talk_id": "667", "lang": ["el", "en", "vi", "it", "ar", "pt-BR", "cs", "id", "es", "ru", "nl", "pt", "zh-Hant", "tr", "zh-Hans", "ro", "pl", "fr", "bg", "uk", "hr", "de", "da", "fa", "hu", "ja", "he", "ko"], "download_link": "https://download.ted.com/talks/RachelArmstrong_2009G", "views": "1,345,901"}