{"outputs":[{"output":{"matches":[{"auto_complete":false,"model_name":"mono-enar.mod","source":{"inflection":"","info":"","lemma":"ago","phonetic":"","pos":"prep","term":"ago"},"targets":[{"context":"","domain":"","entry_id":686,"expressions":[],"info":"","invmeanings":[""],"lemma":"مُنذُ","rank":"","synonym":"","variant":""}]},{"auto_complete":false,"model_name":"mono-enar.mod","source":{"inflection":"","info":"","lemma":"ago","phonetic":"","pos":"adv","term":"ago"},"targets":[{"context":"","domain":"","entry_id":33309,"expressions":[],"info":"","invmeanings":[""],"lemma":"منذ","rank":"","synonym":"","variant":""}]}],"sDictSearch":true}}]}