{"outputs":[{"output":{"matches":[{"auto_complete":false,"model_name":"mono-enar.mod","source":{"inflection":"","info":"","lemma":"apprentice","phonetic":"","pos":"verb","term":"apprentice"},"targets":[{"context":"","domain":"","entry_id":33152,"expressions":[],"info":"","invmeanings":[""],"lemma":"درّب","rank":"","synonym":"","variant":""}]},{"auto_complete":false,"model_name":"mono-enar.mod","source":{"inflection":"","info":"","lemma":"apprentice","phonetic":"","pos":"noun","term":"apprentice"},"targets":[{"context":"","domain":"","entry_id":39468,"expressions":[],"info":"","invmeanings":[""],"lemma":"مُتَدَرِّب","rank":"","synonym":"","variant":""}]}],"sDictSearch":true}}]}