{"outputs":[{"output":{"matches":[{"auto_complete":false,"model_name":"mono-enar.mod","source":{"inflection":"","info":"","lemma":"dejected","phonetic":"","pos":"adj","term":"dejected"},"targets":[{"context":"","domain":"","entry_id":1548,"expressions":[],"info":"","invmeanings":[""],"lemma":"مُكتَئِب","rank":"","synonym":"","variant":""},{"context":"","domain":"","entry_id":1548,"expressions":[],"info":"","invmeanings":[""],"lemma":"انقبض","rank":"","synonym":"","variant":""},{"context":"","domain":"","entry_id":1548,"expressions":[],"info":"","invmeanings":[""],"lemma":"ضاق ب","rank":"","synonym":"","variant":""}]}],"sDictSearch":true}}]}