{"outputs":[{"output":{"matches":[{"auto_complete":false,"model_name":"mono-enar.mod","source":{"inflection":"","info":"","lemma":"discount","phonetic":"","pos":"noun","term":"discount"},"targets":[{"context":"","domain":"","entry_id":18301,"expressions":[],"info":"","invmeanings":[""],"lemma":"خَصم","rank":"","synonym":"","variant":""}]},{"auto_complete":false,"model_name":"mono-enar.mod","source":{"inflection":"","info":"","lemma":"discount","phonetic":"","pos":"verb","term":"discount"},"targets":[{"context":"","domain":"","entry_id":24992,"expressions":[],"info":"","invmeanings":[""],"lemma":"خصم","rank":"","synonym":"","variant":""}]}],"sDictSearch":true}}]}