{"outputs":[{"output":{"matches":[{"auto_complete":false,"model_name":"mono-enar.mod","source":{"inflection":"","info":"","lemma":"drain","phonetic":"","pos":"verb","term":"drained"},"targets":[{"context":"","domain":"","entry_id":24270,"expressions":[],"info":"","invmeanings":[""],"lemma":"صرّف","rank":"","synonym":"","variant":""},{"context":"","domain":"","entry_id":24270,"expressions":[],"info":"","invmeanings":[""],"lemma":"فرّغ","rank":"","synonym":"","variant":""},{"context":"","domain":"","entry_id":24270,"expressions":[],"info":"","invmeanings":[""],"lemma":"نزح","rank":"","synonym":"","variant":""}]},{"auto_complete":false,"model_name":"mono-enar.mod","source":{"inflection":"","info":"","lemma":"drained","phonetic":"","pos":"verb","term":"drained"},"targets":[{"context":"","domain":"","entry_id":42556,"expressions":[],"info":"","invmeanings":[""],"lemma":"مُجَفَّف","rank":"","synonym":"","variant":""}]}],"sDictSearch":true}}]}