{"outputs":[{"output":{"matches":[{"auto_complete":false,"model_name":"mono-enar.mod","source":{"inflection":"","info":"","lemma":"endearing","phonetic":"","pos":"adj","term":"endearing"},"targets":[{"context":"","domain":"","entry_id":26487,"expressions":[],"info":"","invmeanings":[""],"lemma":"مَحْبُوبٌ","rank":"","synonym":"","variant":""}]},{"auto_complete":false,"model_name":"mono-enar.mod","source":{"inflection":"","info":"","lemma":"endear","phonetic":"","pos":"verb","term":"endearing"},"targets":[{"context":"","domain":"","entry_id":29245,"expressions":[],"info":"","invmeanings":[""],"lemma":"حبّب","rank":"","synonym":"","variant":""},{"context":"","domain":"","entry_id":29245,"expressions":[],"info":"","invmeanings":[""],"lemma":"عزّز","rank":"","synonym":"","variant":""}]}],"sDictSearch":true}}]}