{"outputs":[{"output":{"matches":[{"auto_complete":false,"model_name":"mono-enar.mod","source":{"inflection":"","info":"","lemma":"enthuse","phonetic":"","pos":"verb","term":"enthuse"},"targets":[{"context":"","domain":"","entry_id":18123,"expressions":[],"info":"","invmeanings":[""],"lemma":"حمس","rank":"","synonym":"","variant":""},{"context":"","domain":"","entry_id":18123,"expressions":[],"info":"","invmeanings":[""],"lemma":"حمّس","rank":"","synonym":"","variant":""}]}],"sDictSearch":true}}]}