{"outputs":[{"output":{"matches":[{"auto_complete":false,"model_name":"mono-enar.mod","other_expressions":[{"context":"","source":"with the view of","target":"بِقَصدِ"}],"source":{"inflection":"","info":"","lemma":"with","phonetic":"","pos":"prep","term":"with"},"targets":[]},{"auto_complete":false,"model_name":"mono-enar.mod","other_expressions":[{"context":"","source":"with the purpose of","target":"بِغَرَضِ"}],"source":{"inflection":"","info":"","lemma":"with","phonetic":"","pos":"prep","term":"with"},"targets":[]},{"auto_complete":false,"model_name":"mono-enar.mod","other_expressions":[{"context":"","source":"with the help of","target":"بِعَونِ"}],"source":{"inflection":"","info":"","lemma":"with","phonetic":"","pos":"prep","term":"with"},"targets":[]},{"auto_complete":false,"model_name":"mono-enar.mod","other_expressions":[{"context":"","source":"with the exception of","target":"بِاِستِثنَاءِ"}],"source":{"inflection":"","info":"","lemma":"with","phonetic":"","pos":"prep","term":"with"},"targets":[]},{"auto_complete":false,"model_name":"mono-enar.mod","other_expressions":[{"context":"","source":"with no","target":"بِلَا"}],"source":{"inflection":"","info":"","lemma":"with","phonetic":"","pos":"prep","term":"with"},"targets":[]},{"auto_complete":false,"model_name":"mono-enar.mod","other_expressions":[{"context":"","source":"with emphasis on","target":"بِالتَّأكِيدِ"}],"source":{"inflection":"","info":"","lemma":"with","phonetic":"","pos":"prep","term":"with"},"targets":[]},{"auto_complete":false,"model_name":"mono-enar.mod","other_expressions":[{"context":"","source":"with a view to","target":"بِصَدَدِ"}],"source":{"inflection":"","info":"","lemma":"with","phonetic":"","pos":"prep","term":"with"},"targets":[]},{"auto_complete":false,"model_name":"mono-enar.mod","source":{"inflection":"","info":"","lemma":"with","phonetic":"","pos":"prep","term":"with"},"targets":[{"context":"","domain":"","entry_id":28,"expressions":[],"info":"","invmeanings":[""],"lemma":"مَعَ","rank":"","synonym":"","variant":""}]}],"sDictSearch":true}}]}